suzie/__init__.py
suzie/examples.py
suzie/suzie.py
suzie/utils.py
suzie/app_pages/audio_playback.py
suzie/app_pages/audio_recording.py
suzie/app_pages/audio_upload.py
suzie/app_pages/configurations.py
suzie/app_pages/create_minute_notes.py
suzie/app_pages/intro.py
suzie/app_pages/model_instructions.py
suzie/app_pages/transcribe.py
suzie/app_pages/transcribe_edit.py
suzie/tests/test_suzie.py
suzie-0.1.0.dist-info/licenses/LICENSE
suzie-0.1.0.dist-info/METADATA
suzie-0.1.0.dist-info/WHEEL
suzie-0.1.0.dist-info/top_level.txt
suzie-0.1.0.dist-info/RECORD
