Metadata-Version: 2.4
Name: suzie
Version: 0.1.0
Summary: Suzie is an AI assistant with the purpose of summarizing, transcribing and meeting support.
Author-email: Erdogan Taskesen <erdogant@gmail.com>
License: MIT License
Project-URL: Homepage, https://erdogant.github.io/suzie
Project-URL: Download, https://github.com/erdogant/suzie/archive/{version}.tar.gz
Keywords: Python,
Classifier: Programming Language :: Python :: 3
Classifier: Intended Audience :: Education
Classifier: Intended Audience :: Science/Research
Classifier: Operating System :: Unix
Classifier: Operating System :: Microsoft :: Windows
Classifier: Operating System :: MacOS
Classifier: Operating System :: OS Independent
Classifier: Topic :: Scientific/Engineering :: Artificial Intelligence
Classifier: Topic :: Scientific/Engineering :: Bio-Informatics
Classifier: License :: OSI Approved :: MIT License
Requires-Python: >=3
License-File: LICENSE
Requires-Dist: markdown-pdf>=1.3.3
Requires-Dist: openai>=1.60.0
Requires-Dist: streamlit==1.41.1
Requires-Dist: ffmpeg-setpath
Requires-Dist: streamlit-audiorec
Requires-Dist: openai-whisper
Requires-Dist: pypickle
Requires-Dist: llmlight
Dynamic: license-file
